nat/meta/pypi.md
nat/plugins/langchain/__init__.py
nat/plugins/langchain/embedder.py
nat/plugins/langchain/llm.py
nat/plugins/langchain/register.py
nat/plugins/langchain/retriever.py
nat/plugins/langchain/tool_wrapper.py
nat/plugins/langchain/tools/__init__.py
nat/plugins/langchain/tools/code_generation_tool.py
nat/plugins/langchain/tools/register.py
nat/plugins/langchain/tools/tavily_internet_search.py
nat/plugins/langchain/tools/wikipedia_search.py
nvidia_nat_langchain-1.3.1.dist-info/licenses/LICENSE-3rd-party.txt
nvidia_nat_langchain-1.3.1.dist-info/licenses/LICENSE.md
nvidia_nat_langchain-1.3.1.dist-info/METADATA
nvidia_nat_langchain-1.3.1.dist-info/WHEEL
nvidia_nat_langchain-1.3.1.dist-info/entry_points.txt
nvidia_nat_langchain-1.3.1.dist-info/top_level.txt
nvidia_nat_langchain-1.3.1.dist-info/RECORD
