Metadata-Version: 2.4
Name: nvidia-nat-langchain
Version: 1.3.1
Summary: Subpackage for LangChain/LangGraph integration in NeMo Agent toolkit
Author: NVIDIA Corporation
Maintainer: NVIDIA Corporation
License: Apache-2.0
Project-URL: documentation, https://docs.nvidia.com/nemo/agent-toolkit/latest/
Project-URL: source, https://github.com/NVIDIA/NeMo-Agent-Toolkit
Keywords: ai,rag,agents
Classifier: Programming Language :: Python
Classifier: Programming Language :: Python :: 3.11
Classifier: Programming Language :: Python :: 3.12
Classifier: Programming Language :: Python :: 3.13
Requires-Python: <3.14,>=3.11
License-File: LICENSE-3rd-party.txt
License-File: LICENSE.md
Requires-Dist: nvidia-nat==v1.3.1
Requires-Dist: langchain~=0.3.27
Requires-Dist: langchain-aws~=0.2.31
Requires-Dist: langchain-core~=0.3.75
Requires-Dist: langchain-litellm~=0.2.3
Requires-Dist: langchain-milvus~=0.2.1
Requires-Dist: langchain-nvidia-ai-endpoints~=0.3.17
Requires-Dist: langchain-openai~=0.3.32
Requires-Dist: langchain-tavily~=0.2.11
Requires-Dist: langgraph~=0.6.7
Dynamic: license-file
